airkupofrod/__init__.py
airkupofrod/_version.py
airkupofrod/collect.py
airkupofrod/conversions.py
airkupofrod/exception.py
airkupofrod/operator.py
airkupofrod/request_factory.py
airkupofrod-0.7.0.dist-info/LICENSE
airkupofrod-0.7.0.dist-info/METADATA
airkupofrod-0.7.0.dist-info/WHEEL
airkupofrod-0.7.0.dist-info/top_level.txt
airkupofrod-0.7.0.dist-info/RECORD
