Metadata-Version: 2.1
Name: airkupofrod
Version: 0.7.0
Summary: Takes a deployment in your kubernetes cluster and turns its pod template into a KubernetesPodOperator object.
Home-page: https://github.com/rekon-oss/airkupofrod
Author: Reuben Thomas-Davis
Author-email: reuben@rekon.uk
License: UNKNOWN
Platform: UNKNOWN
Classifier: Programming Language :: Python :: 3
Classifier: License :: OSI Approved :: MIT License
Classifier: Operating System :: OS Independent
Requires-Python: >=3.6
Requires-Dist: apache-airflow[kubernetes] (>=1.10)
